fast_layers/__init__.py
fast_layers/layer.py
fast_layers/sequence.py
fast_layers-0.1.7.dist-info/LICENSE
fast_layers-0.1.7.dist-info/METADATA
fast_layers-0.1.7.dist-info/WHEEL
fast_layers-0.1.7.dist-info/top_level.txt
fast_layers-0.1.7.dist-info/RECORD
