Metadata-Version: 2.1
Name: fast-layers
Version: 0.1.7
Summary: Fast-Layers is a python library for Keras and Tensorflow users: The fastest way to build complex deep neural network architectures with sequential models
Home-page: https://github.com/AlexandreMahdhaoui/fast-layers
Author: Alexandre Mahdhaoui
Author-email: alexandre.mahdhaoui@gmail.com
License: MIT
Download-URL: https://github.com/AlexandreMahdhaoui/fast-layers.git
Keywords: keras,tensorflow
Platform: UNKNOWN
Requires-Dist: tensorflow
